<PAMDataset>
  <Metadata domain="IMAGE_STRUCTURE">
    <MDI key="SOURCE_COLOR_SPACE">YCbCr</MDI>
    <MDI key="INTERLEAVE">PIXEL</MDI>
    <MDI key="COMPRESSION">JPEG</MDI>
  </Metadata>
  <PAMRasterBand band="1">
    <Metadata>
      <MDI key="STATISTICS_APPROXIMATE">YES</MDI>
      <MDI key="STATISTICS_MINIMUM">13</MDI>
      <MDI key="STATISTICS_MAXIMUM">51</MDI>
      <MDI key="STATISTICS_MEAN">21.983505249023</MDI>
      <MDI key="STATISTICS_STDDEV">3.2578948608214</MDI>
      <MDI key="STATISTICS_VALID_PERCENT">100</MDI>
    </Metadata>
    <Metadata domain="IMAGE_STRUCTURE">
      <MDI key="COMPRESSION">JPEG</MDI>
    </Metadata>
  </PAMRasterBand>
  <PAMRasterBand band="2">
    <Metadata>
      <MDI key="STATISTICS_APPROXIMATE">YES</MDI>
      <MDI key="STATISTICS_MINIMUM">14</MDI>
      <MDI key="STATISTICS_MAXIMUM">50</MDI>
      <MDI key="STATISTICS_MEAN">21.809326171875</MDI>
      <MDI key="STATISTICS_STDDEV">3.1353231344287</MDI>
      <MDI key="STATISTICS_VALID_PERCENT">100</MDI>
    </Metadata>
    <Metadata domain="IMAGE_STRUCTURE">
      <MDI key="COMPRESSION">JPEG</MDI>
    </Metadata>
  </PAMRasterBand>
  <PAMRasterBand band="3">
    <Metadata>
      <MDI key="STATISTICS_APPROXIMATE">YES</MDI>
      <MDI key="STATISTICS_MINIMUM">12</MDI>
      <MDI key="STATISTICS_MAXIMUM">48</MDI>
      <MDI key="STATISTICS_MEAN">19.953369140625</MDI>
      <MDI key="STATISTICS_STDDEV">3.1571768636712</MDI>
      <MDI key="STATISTICS_VALID_PERCENT">100</MDI>
    </Metadata>
    <Metadata domain="IMAGE_STRUCTURE">
      <MDI key="COMPRESSION">JPEG</MDI>
    </Metadata>
  </PAMRasterBand>
</PAMDataset>
